poc_dashai_plugins_pypi/__init__.py
poc_dashai_plugins_pypi/example.py
poc_dashai_plugins_pypi-0.0.6.dist-info/METADATA
poc_dashai_plugins_pypi-0.0.6.dist-info/WHEEL
poc_dashai_plugins_pypi-0.0.6.dist-info/licenses/LICENSE
poc_dashai_plugins_pypi-0.0.6.dist-info/RECORD
